sandboxapi/__init__.py
sandboxapi/cuckoo.py
sandboxapi/falcon.py
sandboxapi/fireeye.py
sandboxapi/joe.py
sandboxapi/opswat.py
sandboxapi/triage.py
sandboxapi/vmray.py
sandboxapi/wildfire.py
sandboxapi-1.7.1.dist-info/LICENSE
sandboxapi-1.7.1.dist-info/METADATA
sandboxapi-1.7.1.dist-info/WHEEL
sandboxapi-1.7.1.dist-info/top_level.txt
sandboxapi-1.7.1.dist-info/RECORD
