Metadata-Version: 2.1
Name: sandboxapi
Version: 1.7.1
Summary: Minimal, consistent API for building integrations with malware sandboxes.
Home-page: https://github.com/InQuest/python-sandboxapi
Author: InQuest Labs
Author-email: labs@inquest.net
License: GPL
Classifier: Intended Audience :: Developers
Classifier: Intended Audience :: Information Technology
Classifier: Intended Audience :: System Administrators
Classifier: License :: OSI Approved :: GNU General Public License v2 (GPLv2)
Classifier: Operating System :: OS Independent
Classifier: Programming Language :: Python
Classifier: Topic :: Software Development :: Libraries
Classifier: Topic :: Internet
License-File: LICENSE
Requires-Dist: requests
Requires-Dist: jbxapi
Requires-Dist: xmltodict
